staticinteract/__init__.py
staticinteract/interact.py
staticinteract/widgets.py
staticinteract-0.0.3.dist-info/LICENSE
staticinteract-0.0.3.dist-info/METADATA
staticinteract-0.0.3.dist-info/WHEEL
staticinteract-0.0.3.dist-info/top_level.txt
staticinteract-0.0.3.dist-info/RECORD
